superpathlib/__init__.py
superpathlib/base.py
superpathlib/cached_content.py
superpathlib/common_folders.py
superpathlib/content_properties.py
superpathlib/encryption.py
superpathlib/extra_functionality.py
superpathlib/metadata_properties.py
superpathlib/override.py
superpathlib/path.py
superpathlib/py.typed
superpathlib/tags.py
superpathlib/utils.py
superpathlib-2.0.10.dist-info/licenses/LICENSE
superpathlib-2.0.10.dist-info/METADATA
superpathlib-2.0.10.dist-info/WHEEL
superpathlib-2.0.10.dist-info/top_level.txt
superpathlib-2.0.10.dist-info/RECORD
