Metadata-Version: 2.4
Name: superpathlib
Version: 2.0.10
Summary: Extended Pathlib
Author-email: Quinten Roets <qdr2104@columbia.edu>
License-Expression: MIT
Project-URL: Source Code, https://github.com/quintenroets/superpathlib
Requires-Python: >=3.10
License-File: LICENSE
Requires-Dist: simple-classproperty<5,>=4.0.2
Provides-Extra: full
Requires-Dist: dirhash<1,>=0.2.1; extra == "full"
Requires-Dist: numpy<3,>=1.26.4; extra == "full"
Requires-Dist: package-utils<1,>=0.6.1; extra == "full"
Requires-Dist: PyYaml<7,>=6.0.1; extra == "full"
Requires-Dist: xattr<2,>=0.10.1; extra == "full"
Provides-Extra: dev
Requires-Dist: hypothesis<7,>=6.97.1; extra == "dev"
Requires-Dist: package-dev-tools<1,>=0.7.1; extra == "dev"
Requires-Dist: types-PyYaml<7,>=6.0.12.12; extra == "dev"
Requires-Dist: dirhash<1,>=0.2.1; extra == "dev"
Requires-Dist: numpy<3,>=1.26.4; extra == "dev"
Requires-Dist: package-utils<1,>=0.6.1; extra == "dev"
Requires-Dist: PyYaml<7,>=6.0.1; extra == "dev"
Requires-Dist: xattr<2,>=0.10.1; extra == "dev"
Dynamic: license-file
